scruby_full_text/__init__.py
scruby_full_text/plugin.py
scruby_full_text/py.typed
scruby_full_text/settings.py
scruby_full_text-0.5.5.dist-info/licenses/GPL-3.0-LICENSE
scruby_full_text-0.5.5.dist-info/licenses/MIT-LICENSE
scruby_full_text-0.5.5.dist-info/WHEEL
scruby_full_text-0.5.5.dist-info/METADATA
scruby_full_text-0.5.5.dist-info/RECORD
