Metadata-Version: 2.4
Name: scruby-full-text
Version: 0.5.5
Summary: Plugin for Scruby - Full-text search with Manticore Search.
Keywords: plugin,scruby,manticore,search,database
Author: kebasyaty
Author-email: kebasyaty <kebasyaty@gmail.com>
License-Expression: MIT or GPL-3.0-or-later
License-File: GPL-3.0-LICENSE
License-File: MIT-LICENSE
Classifier: Development Status :: 5 - Production/Stable
Classifier: Intended Audience :: Developers
Classifier: License :: OSI Approved :: MIT License
Classifier: License :: OSI Approved :: GNU General Public License v3 or later (GPLv3+)
Classifier: Operating System :: MacOS :: MacOS X
Classifier: Operating System :: Microsoft :: Windows
Classifier: Operating System :: POSIX
Classifier: Operating System :: POSIX :: Linux
Classifier: Programming Language :: Python :: 3
Classifier: Programming Language :: Python :: 3 :: Only
Classifier: Programming Language :: Python :: 3.12
Classifier: Programming Language :: Python :: 3.13
Classifier: Programming Language :: Python :: 3.14
Classifier: Programming Language :: Python :: Implementation :: CPython
Classifier: Topic :: Software Development :: Libraries
Classifier: Topic :: Software Development :: Libraries :: Python Modules
Classifier: Topic :: Database
Classifier: Typing :: Typed
Requires-Dist: anyio>=4.12.1
Requires-Dist: manticoresearch
Requires-Dist: scruby-plugin>=0.2.2
Requires-Dist: xloft>=0.9.8
Requires-Python: >=3.12, <4.0
Project-URL: Bug Tracker, https://github.com/kebasyaty/scruby-full-text/issues
Project-URL: Changelog, https://github.com/kebasyaty/scruby-full-text/blob/v0/CHANGELOG.md
Project-URL: Homepage, https://kebasyaty.github.io/scruby-full-text/
Project-URL: Repository, https://github.com/kebasyaty/scruby-full-text
Project-URL: Source, https://github.com/kebasyaty/scruby-full-text
